<mujoco model="arena">
<include file="agent.xml" />
<visual>
		<headlight ambient="0.5 0.5 0.5" />
		<quality shadowsize="4096" />
	</visual>
	<asset>
	<texture
            name="gym_floor"
            type="2d"
            builtin="checker"
            width="512"
            height="512"
            rgb1="0.2 0.2 0.25"
            rgb2="0.25 0.25 0.3"
        />
        <material
            name="gym_floor"
            texture="gym_floor"
            texrepeat="8 8"
            reflectance="0.1"
            rgba="0.2 0.2 0.25 1"
        />
        <material name="wall" rgba="0.8 0.8 0.8 1" />
	</asset>
	<default>
		<geom condim="3" friction="0.8 0.005 0.0001" />
		<joint damping="0.0005" armature="0.0001" />
		<motor ctrlrange="-1 1" ctrllimited="true" />
	</default>

	<worldbody>
    <light pos="0 0 3" dir="0 0 -1" directional="false" castshadow="true" />
    <light pos="1.5 1.5 2" dir="-1 -1 -1" directional="false" />
    <geom
            name="floor"
            type="plane"
            size="1.6 1.1 0.01"
            material="gym_floor"
            friction="1.1 0.005 0.0001"
        />
    <geom
            name="wall_north"
            type="box"
            pos="0 1.05 0.1"
            size="1.6 0.05 0.1"
            material="wall"
        />
    <geom
            name="wall_south"
            type="box"
            pos="0 -1.05 0.1"
            size="1.6 0.05 0.1"
            material="wall"
        />
    <geom
            name="wall_east"
            type="box"
            pos="1.55 0 0.1"
            size="0.05 1.0 0.1"
            material="wall"
        />
    <geom
            name="wall_west"
            type="box"
            pos="-1.55 0 0.1"
            size="0.05 1.0 0.1"
            material="wall"
        />
</worldbody>
</mujoco>
